{
  "id": "rbd_policydim_aws_s3_usage",
  "name": "AWS S3 Usage Category",
  "rules": [
    {
      "condition": {
        "type": "and",
        "expressions": [
          {
            "type": "dimension_contains",
            "dimension": "service",
            "substring": "AmazonS3",
            "caseInsensitive": true
          },
          {
            "type": "or",
            "expressions": [
              {
                "type": "dimension_contains",
                "dimension": "usage_type",
                "substring": "TimedStorage",
                "caseInsensitive": true
              },
              {
                "type": "dimension_contains",
                "dimension": "usage_type",
                "substring": "Storage",
                "caseInsensitive": true
              }
            ]
          }
        ]
      },
      "value": {
        "text": "Storage"
      }
    },
    {
      "condition": {
        "type": "and",
        "expressions": [
          {
            "type": "dimension_contains",
            "dimension": "service",
            "substring": "AmazonS3",
            "caseInsensitive": true
          },
          {
            "type": "or",
            "expressions": [
              {
                "type": "dimension_contains",
                "dimension": "usage_type",
                "substring": "Requests-Tier1",
                "caseInsensitive": true
              },
              {
                "type": "dimension_contains",
                "dimension": "usage_type",
                "substring": "Requests-Tier2",
                "caseInsensitive": true
              },
              {
                "type": "dimension_contains",
                "dimension": "usage_type",
                "substring": "Requests-Tier3",
                "caseInsensitive": true
              },
              {
                "type": "dimension_contains",
                "dimension": "usage_type",
                "substring": "Requests-SIA",
                "caseInsensitive": true
              },
              {
                "type": "dimension_contains",
                "dimension": "usage_type",
                "substring": "Requests-ZIA",
                "caseInsensitive": true
              },
              {
                "type": "dimension_contains",
                "dimension": "usage_type",
                "substring": "Requests-GDA",
                "caseInsensitive": true
              },
              {
                "type": "dimension_contains",
                "dimension": "usage_type",
                "substring": "Requests-Inventory",
                "caseInsensitive": true
              },
              {
                "type": "dimension_contains",
                "dimension": "usage_type",
                "substring": "Requests-GIR",
                "caseInsensitive": true
              },
              {
                "type": "dimension_contains",
                "dimension": "usage_type",
                "substring": "Requests-GFR",
                "caseInsensitive": true
              }
            ]
          }
        ]
      },
      "value": {
        "text": "Requests"
      }
    },
    {
      "condition": {
        "type": "and",
        "expressions": [
          {
            "type": "dimension_contains",
            "dimension": "service",
            "substring": "AmazonS3",
            "caseInsensitive": true
          },
          {
            "type": "or",
            "expressions": [
              {
                "type": "and",
                "expressions": [
                  {
                    "type": "dimension_contains",
                    "dimension": "usage_type",
                    "substring": "DataTransfer",
                    "caseInsensitive": true
                  },
                  {
                    "type": "or",
                    "expressions": [
                      {
                        "type": "dimension_contains",
                        "dimension": "usage_type",
                        "substring": "In",
                        "caseInsensitive": true
                      },
                      {
                        "type": "dimension_contains",
                        "dimension": "usage_type",
                        "substring": "Out",
                        "caseInsensitive": true
                      },
                      {
                        "type": "dimension_contains",
                        "dimension": "usage_type",
                        "substring": "Regional",
                        "caseInsensitive": true
                      }
                    ]
                  }
                ]
              },
              {
                "type": "and",
                "expressions": [
                  {
                    "type": "dimension_contains",
                    "dimension": "usage_type",
                    "substring": "Bytes",
                    "caseInsensitive": true
                  },
                  {
                    "type": "or",
                    "expressions": [
                      {
                        "type": "dimension_contains",
                        "dimension": "usage_type",
                        "substring": "In",
                        "caseInsensitive": true
                      },
                      {
                        "type": "dimension_contains",
                        "dimension": "usage_type",
                        "substring": "Out",
                        "caseInsensitive": true
                      },
                      {
                        "type": "dimension_contains",
                        "dimension": "usage_type",
                        "substring": "Regional",
                        "caseInsensitive": true
                      }
                    ]
                  }
                ]
              }
            ]
          }
        ]
      },
      "value": {
        "text": "Data Transfer"
      }
    },
    {
      "condition": {
        "type": "and",
        "expressions": [
          {
            "type": "dimension_contains",
            "dimension": "service",
            "substring": "AmazonS3",
            "caseInsensitive": true
          },
          {
            "type": "or",
            "expressions": [
              {
                "type": "dimension_contains",
                "dimension": "usage_type",
                "substring": "Retrieval",
                "caseInsensitive": true
              },
              {
                "type": "dimension_contains",
                "dimension": "usage_type",
                "substring": "Restore",
                "caseInsensitive": true
              },
              {
                "type": "and",
                "expressions": [
                  {
                    "type": "dimension_contains",
                    "dimension": "usage_type",
                    "substring": "Select",
                    "caseInsensitive": true
                  },
                  {
                    "type": "dimension_contains",
                    "dimension": "usage_type",
                    "substring": "Bytes",
                    "caseInsensitive": true
                  }
                ]
              }
            ]
          }
        ]
      },
      "value": {
        "text": "Data Retrieval"
      }
    },
    {
      "condition": {
        "type": "and",
        "expressions": [
          {
            "type": "dimension_contains",
            "dimension": "service",
            "substring": "AmazonS3",
            "caseInsensitive": true
          },
          {
            "type": "or",
            "expressions": [
              {
                "type": "dimension_contains",
                "dimension": "usage_type",
                "substring": "Monitoring-Automation-INT",
                "caseInsensitive": true
              },
              {
                "type": "dimension_contains",
                "dimension": "usage_type",
                "substring": "StorageAnalytics",
                "caseInsensitive": true
              },
              {
                "type": "dimension_contains",
                "dimension": "usage_type",
                "substring": "Inventory",
                "caseInsensitive": true
              },
              {
                "type": "dimension_contains",
                "dimension": "usage_type",
                "substring": "Management",
                "caseInsensitive": true
              },
              {
                "type": "dimension_contains",
                "dimension": "usage_type",
                "substring": "Analytics",
                "caseInsensitive": true
              },
              {
                "type": "dimension_contains",
                "dimension": "usage_type",
                "substring": "IntelligentTiering",
                "caseInsensitive": true
              }
            ]
          }
        ]
      },
      "value": {
        "text": "Management & Analytics"
      }
    },
    {
      "condition": {
        "type": "and",
        "expressions": [
          {
            "type": "dimension_contains",
            "dimension": "service",
            "substring": "AmazonS3",
            "caseInsensitive": true
          },
          {
            "type": "or",
            "expressions": [
              {
                "type": "dimension_contains",
                "dimension": "usage_type",
                "substring": "Replication",
                "caseInsensitive": true
              },
              {
                "type": "dimension_contains",
                "dimension": "usage_type",
                "substring": "CRR",
                "caseInsensitive": true
              },
              {
                "type": "dimension_contains",
                "dimension": "usage_type",
                "substring": "SRR",
                "caseInsensitive": true
              }
            ]
          }
        ]
      },
      "value": {
        "text": "Replication"
      }
    },
    {
      "condition": {
        "type": "and",
        "expressions": [
          {
            "type": "dimension_contains",
            "dimension": "service",
            "substring": "AmazonS3",
            "caseInsensitive": true
          },
          {
            "type": "or",
            "expressions": [
              {
                "type": "dimension_contains",
                "dimension": "usage_type",
                "substring": "Fee",
                "caseInsensitive": true
              },
              {
                "type": "dimension_contains",
                "dimension": "usage_type",
                "substring": "Charge",
                "caseInsensitive": true
              },
              {
                "type": "dimension_contains",
                "dimension": "usage_type",
                "substring": "Acceleration",
                "caseInsensitive": true
              },
              {
                "type": "dimension_contains",
                "dimension": "usage_type",
                "substring": "CloudFront",
                "caseInsensitive": true
              },
              {
                "type": "or",
                "expressions": [
                  {
                    "type": "dimension_contains",
                    "dimension": "usage_type",
                    "substring": "EarlyDelete",
                    "caseInsensitive": true
                  },
                  {
                    "type": "and",
                    "expressions": [
                      {
                        "type": "dimension_contains",
                        "dimension": "usage_type",
                        "substring": "Delete",
                        "caseInsensitive": true
                      },
                      {
                        "type": "or",
                        "expressions": [
                          {
                            "type": "dimension_contains",
                            "dimension": "usage_type",
                            "substring": "SIA",
                            "caseInsensitive": true
                          },
                          {
                            "type": "dimension_contains",
                            "dimension": "usage_type",
                            "substring": "ZIA",
                            "caseInsensitive": true
                          },
                          {
                            "type": "dimension_contains",
                            "dimension": "usage_type",
                            "substring": "Glacier",
                            "caseInsensitive": true
                          }
                        ]
                      }
                    ]
                  }
                ]
              }
            ]
          }
        ]
      },
      "value": {
        "text": "Other Fees"
      }
    }
  ]
}
