[
  {
    "name": "East US",
    "region": "eastus",
    "cheaper": null,
    "cheaper_ratio": null
  },
  {
    "name": "East US 2",
    "region": "eastus2",
    "cheaper": null,
    "cheaper_ratio": null
  },
  {
    "name": "South Central US",
    "region": "southcentralus",
    "cheaper": null,
    "cheaper_ratio": null
  },
  {
    "name": "West US 2",
    "region": "westus2",
    "cheaper": null,
    "cheaper_ratio": null
  },
  {
    "name": "West US 3",
    "region": "westus3",
    "cheaper": null,
    "cheaper_ratio": null
  },
  {
    "name": "Australia East",
    "region": "australiaeast",
    "cheaper": "southeastasia",
    "cheaper_ratio": 0.91
  },
  {
    "name": "Southeast Asia",
    "region": "southeastasia",
    "cheaper": null,
    "cheaper_ratio": null
  },
  {
    "name": "North Europe",
    "region": "northeurope",
    "cheaper": null,
    "cheaper_ratio": null
  },
  {
    "name": "Sweden Central",
    "region": "swedencentral",
    "cheaper": null,
    "cheaper_ratio": null
  },
  {
    "name": "UK South",
    "region": "uksouth",
    "cheaper": null,
    "cheaper_ratio": null
  },
  {
    "name": "West Europe",
    "region": "westeurope",
    "cheaper": "uksouth",
    "cheaper_ratio": 0.96
  },
  {
    "name": "Central US",
    "region": "centralus",
    "cheaper": null,
    "cheaper_ratio": null
  },
  {
    "name": "South Africa North",
    "region": "southafricanorth",
    "cheaper": null,
    "cheaper_ratio": null
  },
  {
    "name": "Central India",
    "region": "centralindia",
    "cheaper": null,
    "cheaper_ratio": null
  },
  {
    "name": "East Asia",
    "region": "eastasia",
    "cheaper": "southeastasia",
    "cheaper_ratio": 0.93
  },
  {
    "name": "Japan East",
    "region": "japaneast",
    "cheaper": "koreacentral",
    "cheaper_ratio": 0.93
  },
  {
    "name": "Korea Central",
    "region": "koreacentral",
    "cheaper": null,
    "cheaper_ratio": null
  },
  {
    "name": "Canada Central",
    "region": "canadacentral",
    "cheaper": null,
    "cheaper_ratio": null
  },
  {
    "name": "France Central",
    "region": "francecentral",
    "cheaper": "northeurope",
    "cheaper_ratio": 0.86
  },
  {
    "name": "Germany West Central",
    "region": "germanywestcentral",
    "cheaper": "northeurope",
    "cheaper_ratio": 0.86
  },
  {
    "name": "Norway East",
    "region": "norwayeast",
    "cheaper": "northeurope",
    "cheaper_ratio": 0.86
  },
  {
    "name": "Poland Central",
    "region": "polandcentral",
    "cheaper": null,
    "cheaper_ratio": null
  },
  {
    "name": "Switzerland North",
    "region": "switzerlandnorth",
    "cheaper": "northeurope",
    "cheaper_ratio": 0.75
  },
  {
    "name": "UAE North",
    "region": "uaenorth",
    "cheaper": null,
    "cheaper_ratio": null
  },
  {
    "name": "Brazil South",
    "region": "brazilsouth",
    "cheaper": null,
    "cheaper_ratio": null
  },
  {
    "name": "Central US EUAP",
    "region": "centraluseuap",
    "cheaper": null,
    "cheaper_ratio": null
  },
  {
    "name": "Qatar Central",
    "region": "qatarcentral",
    "cheaper": "uaenorth",
    "cheaper_ratio": 0.86
  },
  {
    "name": "Central US (Stage)",
    "region": "centralusstage",
    "cheaper": null,
    "cheaper_ratio": null
  },
  {
    "name": "East US (Stage)",
    "region": "eastusstage",
    "cheaper": null,
    "cheaper_ratio": null
  },
  {
    "name": "East US 2 (Stage)",
    "region": "eastus2stage",
    "cheaper": null,
    "cheaper_ratio": null
  },
  {
    "name": "North Central US (Stage)",
    "region": "northcentralusstage",
    "cheaper": null,
    "cheaper_ratio": null
  },
  {
    "name": "South Central US (Stage)",
    "region": "southcentralusstage",
    "cheaper": null,
    "cheaper_ratio": null
  },
  {
    "name": "West US (Stage)",
    "region": "westusstage",
    "cheaper": null,
    "cheaper_ratio": null
  },
  {
    "name": "West US 2 (Stage)",
    "region": "westus2stage",
    "cheaper": null,
    "cheaper_ratio": null
  },
  {
    "name": "Asia",
    "region": "asia",
    "cheaper": null,
    "cheaper_ratio": null
  },
  {
    "name": "Asia Pacific",
    "region": "asiapacific",
    "cheaper": null,
    "cheaper_ratio": null
  },
  {
    "name": "Australia",
    "region": "australia",
    "cheaper": null,
    "cheaper_ratio": null
  },
  {
    "name": "Brazil",
    "region": "brazil",
    "cheaper": null,
    "cheaper_ratio": null
  },
  {
    "name": "Canada",
    "region": "canada",
    "cheaper": null,
    "cheaper_ratio": null
  },
  {
    "name": "Europe",
    "region": "europe",
    "cheaper": null,
    "cheaper_ratio": null
  },
  {
    "name": "France",
    "region": "france",
    "cheaper": null,
    "cheaper_ratio": null
  },
  {
    "name": "Germany",
    "region": "germany",
    "cheaper": null,
    "cheaper_ratio": null
  },
  {
    "name": "Global",
    "region": "global",
    "cheaper": null,
    "cheaper_ratio": null
  },
  {
    "name": "India",
    "region": "india",
    "cheaper": null,
    "cheaper_ratio": null
  },
  {
    "name": "Japan",
    "region": "japan",
    "cheaper": null,
    "cheaper_ratio": null
  },
  {
    "name": "Korea",
    "region": "korea",
    "cheaper": null,
    "cheaper_ratio": null
  },
  {
    "name": "Norway",
    "region": "norway",
    "cheaper": null,
    "cheaper_ratio": null
  },
  {
    "name": "Singapore",
    "region": "singapore",
    "cheaper": null,
    "cheaper_ratio": null
  },
  {
    "name": "South Africa",
    "region": "southafrica",
    "cheaper": null,
    "cheaper_ratio": null
  },
  {
    "name": "Switzerland",
    "region": "switzerland",
    "cheaper": null,
    "cheaper_ratio": null
  },
  {
    "name": "United Arab Emirates",
    "region": "uae",
    "cheaper": null,
    "cheaper_ratio": null
  },
  {
    "name": "United Kingdom",
    "region": "uk",
    "cheaper": null,
    "cheaper_ratio": null
  },
  {
    "name": "United States",
    "region": "unitedstates",
    "cheaper": null,
    "cheaper_ratio": null
  },
  {
    "name": "United States EUAP",
    "region": "unitedstateseuap",
    "cheaper": null,
    "cheaper_ratio": null
  },
  {
    "name": "East Asia (Stage)",
    "region": "eastasiastage",
    "cheaper": null,
    "cheaper_ratio": null
  },
  {
    "name": "Southeast Asia (Stage)",
    "region": "southeastasiastage",
    "cheaper": null,
    "cheaper_ratio": null
  },
  {
    "name": "Brazil US",
    "region": "brazilus",
    "cheaper": null,
    "cheaper_ratio": null
  },
  {
    "name": "East US STG",
    "region": "eastusstg",
    "cheaper": null,
    "cheaper_ratio": null
  },
  {
    "name": "North Central US",
    "region": "northcentralus",
    "cheaper": null,
    "cheaper_ratio": null
  },
  {
    "name": "West US",
    "region": "westus",
    "cheaper": "westus2",
    "cheaper_ratio": 0.87
  },
  {
    "name": "Jio India West",
    "region": "jioindiawest",
    "cheaper": null,
    "cheaper_ratio": null
  },
  {
    "name": "East US 2 EUAP",
    "region": "eastus2euap",
    "cheaper": null,
    "cheaper_ratio": null
  },
  {
    "name": "South Central US STG",
    "region": "southcentralusstg",
    "cheaper": null,
    "cheaper_ratio": null
  },
  {
    "name": "West Central US",
    "region": "westcentralus",
    "cheaper": null,
    "cheaper_ratio": null
  },
  {
    "name": "South Africa West",
    "region": "southafricawest",
    "cheaper": null,
    "cheaper_ratio": null
  },
  {
    "name": "Australia Central",
    "region": "australiacentral",
    "cheaper": null,
    "cheaper_ratio": null
  },
  {
    "name": "Australia Central 2",
    "region": "australiacentral2",
    "cheaper": null,
    "cheaper_ratio": null
  },
  {
    "name": "Australia Southeast",
    "region": "australiasoutheast",
    "cheaper": "southeastasia",
    "cheaper_ratio": 0.91
  },
  {
    "name": "Japan West",
    "region": "japanwest",
    "cheaper": null,
    "cheaper_ratio": null
  },
  {
    "name": "Jio India Central",
    "region": "jioindiacentral",
    "cheaper": null,
    "cheaper_ratio": null
  },
  {
    "name": "Korea South",
    "region": "koreasouth",
    "cheaper": null,
    "cheaper_ratio": null
  },
  {
    "name": "South India",
    "region": "southindia",
    "cheaper": null,
    "cheaper_ratio": null
  },
  {
    "name": "West India",
    "region": "westindia",
    "cheaper": null,
    "cheaper_ratio": null
  },
  {
    "name": "Canada East",
    "region": "canadaeast",
    "cheaper": null,
    "cheaper_ratio": null
  },
  {
    "name": "France South",
    "region": "francesouth",
    "cheaper": null,
    "cheaper_ratio": null
  },
  {
    "name": "Germany North",
    "region": "germanynorth",
    "cheaper": null,
    "cheaper_ratio": null
  },
  {
    "name": "Norway West",
    "region": "norwaywest",
    "cheaper": null,
    "cheaper_ratio": null
  },
  {
    "name": "Switzerland West",
    "region": "switzerlandwest",
    "cheaper": "northeurope",
    "cheaper_ratio": 0.75
  },
  {
    "name": "UK West",
    "region": "ukwest",
    "cheaper": null,
    "cheaper_ratio": null
  },
  {
    "name": "UAE Central",
    "region": "uaecentral",
    "cheaper": null,
    "cheaper_ratio": null
  },
  {
    "name": "Brazil Southeast",
    "region": "brazilsoutheast",
    "cheaper": null,
    "cheaper_ratio": null
  },
  {
    "name": "Spain Central",
    "region": "spaincentral",
    "cheaper": null,
    "cheaper_ratio": null
  },
  {
    "name": "Italy North",
    "region": "italynorth",
    "cheaper": "northeurope",
    "cheaper_ratio": 0.86
  },
  {
    "name": "Mexico Central",
    "region": "mexicocentral",
    "cheaper": null,
    "cheaper_ratio": null
  },
  {
    "name": "Israel Central",
    "region": "israelcentral",
    "cheaper": "northeurope",
    "cheaper_ratio": 0.86
  },
  {
    "name": "New Zealand North",
    "region": "newzealandnorth",
    "cheaper": "australiaeast",
    "cheaper_ratio": 0.95
  }
]
